conductor/ConductorWorker.py
conductor/FrinxConductorWrapper.py
conductor/__init__.py
conductor/conductor.py
frinx_conductor_client-2.0.0.dist-info/METADATA
frinx_conductor_client-2.0.0.dist-info/WHEEL
frinx_conductor_client-2.0.0.dist-info/top_level.txt
frinx_conductor_client-2.0.0.dist-info/RECORD
